afs2datasource/DBManager.py
afs2datasource/__init__.py
afs2datasource/apmDSHelper.py
afs2datasource/azureBlobHelper.py
afs2datasource/constant.py
afs2datasource/dataHubHelper.py
afs2datasource/helper.py
afs2datasource/influxHelper.py
afs2datasource/mongoHelper.py
afs2datasource/mysqlHelper.py
afs2datasource/oracleDBHepler.py
afs2datasource/postgresHelper.py
afs2datasource/s3Helper.py
afs2datasource/sqlServerHelper.py
afs2datasource/utils.py
test/PostgresTest.py
test/S3test.py
test/Titanic.py
test/__init__.py
test/awsTest.py
test/azureBlobTest.py
test/datahubTest.py
test/localFile.py
test/mysqlTest.py
test/queryStr.py
test/test.py
test/testmySqlHelper.py
afs2_datasource-3.8.2.dist-info/LICENSE
afs2_datasource-3.8.2.dist-info/METADATA
afs2_datasource-3.8.2.dist-info/WHEEL
afs2_datasource-3.8.2.dist-info/top_level.txt
afs2_datasource-3.8.2.dist-info/RECORD
