Metadata-Version: 2.1
Name: afs2-datasource
Version: 3.8.2
Summary: For AFS developer to access Datasource
Home-page: https://github.com/stacy0416/afs2-datasource
Author: WISE-PaaS/AFS
Author-email: stacy.yeh@advantech.com.tw
License: Apache License 2.0
Keywords: AFS
Platform: UNKNOWN
License-File: LICENSE
Requires-Dist: pymongo (==3.7.2)
Requires-Dist: pandas (<2.0,>=1.0.0)
Requires-Dist: psycopg2-binary (==2.8.1)
Requires-Dist: influxdb (==5.2.2)
Requires-Dist: boto3 (<=1.17)
Requires-Dist: requests (==2.22.0)
Requires-Dist: motor (==2.0.0)
Requires-Dist: azure-storage-blob (==2.0.1)
Requires-Dist: mysql-connector-python (==8.0.26)
Requires-Dist: cx-Oracle (==8.3.0)
Requires-Dist: sqlalchemy (==1.4.27)
Requires-Dist: pyodbc (==4.0.32)
